extract_templates.py
django_extract_templates-0.1.0.data/scripts/extract_templates.py
django_extract_templates-0.1.0.dist-info/LICENSE
django_extract_templates-0.1.0.dist-info/METADATA
django_extract_templates-0.1.0.dist-info/WHEEL
django_extract_templates-0.1.0.dist-info/entry_points.txt
django_extract_templates-0.1.0.dist-info/top_level.txt
django_extract_templates-0.1.0.dist-info/RECORD
